zdppy_mysql/__init__.py
zdppy_mysql/_auth.py
zdppy_mysql/_compat.py
zdppy_mysql/_socketio.py
zdppy_mysql/charset.py
zdppy_mysql/connections.py
zdppy_mysql/constants/__init__.py
zdppy_mysql/constants/CLIENT.py
zdppy_mysql/constants/COMMAND.py
zdppy_mysql/constants/CR.py
zdppy_mysql/constants/ER.py
zdppy_mysql/constants/FIELD_TYPE.py
zdppy_mysql/constants/FLAG.py
zdppy_mysql/constants/SERVER_STATUS.py
zdppy_mysql/converters.py
zdppy_mysql/cursors.py
zdppy_mysql/err.py
zdppy_mysql/exceptions.py
zdppy_mysql/json_encoder.py
zdppy_mysql/mysql.py
zdppy_mysql/optionfile.py
zdppy_mysql/protocol.py
zdppy_mysql/sql.py
zdppy_mysql/times.py
zdppy_mysql/util.py
zdppy_mysql-0.2.5.dist-info/LICENSE
zdppy_mysql-0.2.5.dist-info/WHEEL
zdppy_mysql-0.2.5.dist-info/METADATA
zdppy_mysql-0.2.5.dist-info/RECORD
