Metadata-Version: 2.1
Name: zdppy-mysql
Version: 0.2.5
Summary: 使用python操作MySQL,同步版本,支持事务
Author: zhangdapeng
Author-email: pygosuperman@outlook.com
Requires-Python: >=3.9,<4.0
Classifier: Programming Language :: Python :: 3
Classifier: Programming Language :: Python :: 3.10
Classifier: Programming Language :: Python :: 3.9
